skylog/__init__.py
skylog/client.py
skylog/exception.py
skylog/integration/__init__.py
skylog/integration/abc.py
skylog/integration/config.py
skylog/integration/data_classes.py
skylog/integration/utils.py
skylog_sdk-0.1.15.dist-info/LICENSE
skylog_sdk-0.1.15.dist-info/METADATA
skylog_sdk-0.1.15.dist-info/WHEEL
skylog_sdk-0.1.15.dist-info/RECORD
