Metadata-Version: 2.3
Name: skylog-sdk
Version: 0.1.15
Summary: skylog python sdk
Author: vahidtwo
Author-email: vahidtwo@gmail.com
Requires-Python: >=3.8.12
Classifier: Programming Language :: Python :: 3
Classifier: Programming Language :: Python :: 3.9
Classifier: Programming Language :: Python :: 3.10
Classifier: Programming Language :: Python :: 3.11
Classifier: Programming Language :: Python :: 3.12
Classifier: Programming Language :: Python :: 3.13
Requires-Dist: python-decouple (>=3.6)
Requires-Dist: requests (>=2.31)
Project-URL: Documentation, https://vahidtwo.github.io/skylog-sdk/
Project-URL: Repository, https://github.com/vahidtwo/skylog-sdk
